twitch_info/__init__.py
twitch_info/twitch_info.py
twitch_info-2.3.dist-info/LICENSE
twitch_info-2.3.dist-info/METADATA
twitch_info-2.3.dist-info/WHEEL
twitch_info-2.3.dist-info/top_level.txt
twitch_info-2.3.dist-info/RECORD
