Metadata-Version: 2.1
Name: twitch-info
Version: 2.3
Summary: Get information about a twitch channels and streams
Home-page: UNKNOWN
Author: Feytus
Author-email: feytusinho@gmail.com
License: UNKNOWN
Keywords: python,stream,twitch,channel,information,info
Platform: UNKNOWN
Classifier: Development Status :: 4 - Beta
Classifier: License :: OSI Approved :: MIT License
Classifier: Intended Audience :: Developers
Classifier: Programming Language :: Python :: 3
Classifier: Operating System :: Unix
Classifier: Operating System :: MacOS :: MacOS X
Classifier: Operating System :: Microsoft :: Windows
License-File: LICENSE
Requires-Dist: requests
